API_pkg/Sensor.py
API_pkg/Setup.py
API_pkg/__init__.py
API_pkg/application_console.py
API_pkg/application_file.py
API_StevenThomi-0.0.1.dist-info/LICENSE
API_StevenThomi-0.0.1.dist-info/METADATA
API_StevenThomi-0.0.1.dist-info/WHEEL
API_StevenThomi-0.0.1.dist-info/top_level.txt
API_StevenThomi-0.0.1.dist-info/RECORD
