Metadata-Version: 2.1
Name: API-StevenThomi
Version: 0.0.1
Summary: A temperature and luminosity sensor API package designed for Raspberry Pi
Home-page: https://github.com/StevenThomi/eee3097s_project
Author: Steven Thomi
Author-email: stevenkthomi@gmail.com
License: UNKNOWN
Platform: UNKNOWN
Classifier: Programming Language :: Python :: 3
Classifier: License :: OSI Approved :: MIT License
Classifier: Operating System :: OS Independent
Requires-Python: >=3.6
